hurnet_fx_tensor/__init__.py
hurnet_fx_tensor/hurnet_fx_tensor.py
hurnet_fx_tensor-1.0.2.dist-info/LICENSE.txt
hurnet_fx_tensor-1.0.2.dist-info/METADATA
hurnet_fx_tensor-1.0.2.dist-info/WHEEL
hurnet_fx_tensor-1.0.2.dist-info/top_level.txt
hurnet_fx_tensor-1.0.2.dist-info/RECORD
