Metadata-Version: 2.1
Name: hurnet-fx-tensor
Version: 1.0.2
Home-page: https://github.com/
Author: SAPIENS TECHNOLOGY
License: Proprietary Software
License-File: LICENSE.txt
Requires-Dist: numpy
